setup.py
resin/__init__.py
resin/application.py
resin/baseapi.py
resin/device.py
resin/environment_variables.py
resin/exceptions.py
resin/resources.py
resin.egg-info/PKG-INFO
resin.egg-info/SOURCES.txt
resin.egg-info/dependency_links.txt
resin.egg-info/not-zip-safe
resin.egg-info/pbr.json
resin.egg-info/requires.txt
resin.egg-info/top_level.txt