Metadata-Version: 1.0
Name: resin
Version: 0.1.2
Summary: Thin wrapper for resin api[work in progress]
Home-page: http://github.com/craig-mulligan/resin-python-api-wrapper
Author: craig-mulligan
Author-email: craig@resin.io
License: MIT
Platform: UNKNOWN
